qfragment/__init__.py
qfragment/feedback.py
qfragment/infinitive_phrase_detect.py
qfragment/participlevocabindex.csv
qfragment/subject_verb_agreement.py
qfragment/sva.py
qfragment/sva_rule_based.py
qfragment/test_agreement.py
qfragment/models/participle_model.tfl.data-00000-of-00001
qfragment/models/participle_model.tfl.index
qfragment/models/participle_model.tfl.meta
qfragment/models/subject_verb_agreement_model.tfl.data-00000-of-00001
qfragment/models/subject_verb_agreement_model.tfl.index
qfragment/models/subject_verb_agreement_model.tfl.meta
qfragment/vendor/LanguageTool-4.1/CHANGES.md
qfragment/vendor/LanguageTool-4.1/CHANGES.txt
qfragment/vendor/LanguageTool-4.1/COPYING.txt
qfragment/vendor/LanguageTool-4.1/README.md
qfragment/vendor/LanguageTool-4.1/languagetool-commandline.jar
qfragment/vendor/LanguageTool-4.1/languagetool-server.jar
qfragment/vendor/LanguageTool-4.1/languagetool.jar
qfragment/vendor/LanguageTool-4.1/test.txt
qfragment/vendor/LanguageTool-4.1/testrules.bat
qfragment/vendor/LanguageTool-4.1/testrules.sh
qfragment/vendor/LanguageTool-4.1/META-INF/MANIFEST.MF
qfragment/vendor/LanguageTool-4.1/META-INF/maven/org.languagetool/language-all/pom.properties
qfragment/vendor/LanguageTool-4.1/META-INF/maven/org.languagetool/language-all/pom.xml
qfragment/vendor/LanguageTool-4.1/META-INF/maven/org.languagetool/language-ast/pom.properties
qfragment/vendor/LanguageTool-4.1/META-INF/maven/org.languagetool/language-ast/pom.xml
qfragment/vendor/LanguageTool-4.1/META-INF/maven/org.languagetool/language-be/pom.properties
qfragment/vendor/LanguageTool-4.1/META-INF/maven/org.languagetool/language-be/pom.xml
qfragment/vendor/LanguageTool-4.1/META-INF/maven/org.languagetool/language-br/pom.properties
qfragment/vendor/LanguageTool-4.1/META-INF/maven/org.languagetool/language-br/pom.xml
qfragment/vendor/LanguageTool-4.1/META-INF/maven/org.languagetool/language-ca/pom.properties
qfragment-0.0.26.dist-info/DESCRIPTION.rst
qfragment-0.0.26.dist-info/METADATA
qfragment-0.0.26.dist-info/RECORD
qfragment-0.0.26.dist-info/WHEEL
qfragment-0.0.26.dist-info/dependency_links.txt
qfragment-0.0.26.dist-info/metadata.json
qfragment-0.0.26.dist-info/top_level.txt
